{
  "@context": "https://linked.art/ns/v1/linked-art.json",
  "id": "https://collectionapi.metmuseum.org/public/collection/v1/objects/262098",
  "type": "HumanMadeObject",
  "identified_by": [
    {
      "id": "http://lod.example.org/museum/Identifier/46",
      "type": "Identifier",
      "content": 262098,
      "classified_as": [
        {
          "id": "http://vocab.getty.edu/aat/300404621",
          "type": "Type",
          "_label": "Local Number"
        }
      ]
    },
    {
      "id": "http://lod.example.org/museum/Identifier/47",
      "type": "Identifier",
      "content": "1977.657.1",
      "classified_as": [
        {
          "id": "http://vocab.getty.edu/aat/300312355",
          "type": "Type",
          "_label": "Accession Number"
        }
      ]
    },
    {
      "id": "http://lod.example.org/museum/Name/118",
      "type": "Name",
      "content": "[Looking from Garage to Studio Door, Abiquiu, New Mexico]",
      "classified_as": [
        {
          "id": "http://vocab.getty.edu/aat/300195168",
          "type": "Type",
          "_label": "Title"
        }
      ]
    }
  ],
  "produced_by": {
    "id": "http://lod.example.org/museum/Production/23",
    "type": "Production",
    "timespan": {
      "id": "http://lod.example.org/museum/TimeSpan/69",
      "type": "TimeSpan",
      "begin_of_the_begin": 1957,
      "end_of_the_end": 1958,
      "identified_by": [
        {
          "id": "http://lod.example.org/museum/Name/119",
          "type": "Name",
          "content": "1957\u201358"
        }
      ]
    },
    "carried_out_by": [
      {
        "id": "http://lod.example.org/museum/Person/23",
        "type": "Person",
        "identified_by": [
          {
            "id": "http://lod.example.org/museum/Name/120",
            "type": "Name",
            "content": "Georgia O'Keeffe"
          }
        ],
        "referred_to_by": [
          {
            "id": "http://lod.example.org/museum/LinguisticObject/191",
            "type": "LinguisticObject",
            "content": "American, Sun Prairie, Wisconsin 1887\u20131986 Santa Fe, New Mexico",
            "classified_as": [
              {
                "id": "http://vocab.getty.edu/aat/300080102",
                "type": "Type",
                "_label": "Biography Statement"
              },
              {
                "id": "http://vocab.getty.edu/aat/300418049",
                "type": "Type",
                "_label": "Brief Text"
              }
            ]
          }
        ],
        "classified_as": [
          {
            "id": "http://vocab.getty.edu/aat/300107956",
            "type": "Type",
            "_label": "American",
            "classified_as": [
              {
                "id": "http://vocab.getty.edu/aat/300379842",
                "type": "Type",
                "_label": "Nationality"
              }
            ]
          }
        ],
        "born": {
          "id": "http://lod.example.org/museum/Birth/23",
          "type": "Birth",
          "timespan": {
            "id": "http://lod.example.org/museum/TimeSpan/70",
            "type": "TimeSpan",
            "begin_of_the_begin": "1887",
            "end_of_the_end": "1887",
            "identified_by": [
              {
                "id": "http://lod.example.org/museum/Name/121",
                "type": "Name",
                "content": "1887"
              }
            ]
          }
        },
        "died": {
          "id": "http://lod.example.org/museum/Death/23",
          "type": "Death",
          "timespan": {
            "id": "http://lod.example.org/museum/TimeSpan/71",
            "type": "TimeSpan",
            "begin_of_the_begin": "1986",
            "end_of_the_end": "1986",
            "identified_by": [
              {
                "id": "http://lod.example.org/museum/Name/122",
                "type": "Name",
                "content": "1887"
              }
            ]
          }
        }
      }
    ]
  },
  "referred_to_by": [
    {
      "id": "http://lod.example.org/museum/LinguisticObject/192",
      "type": "LinguisticObject",
      "content": "Gelatin silver print",
      "classified_as": [
        {
          "id": "http://vocab.getty.edu/aat/300010358",
          "type": "Type",
          "_label": "Material Statement"
        },
        {
          "id": "http://vocab.getty.edu/aat/300418049",
          "type": "Type",
          "_label": "Brief Text"
        }
      ]
    },
    {
      "id": "http://lod.example.org/museum/LinguisticObject/193",
      "type": "LinguisticObject",
      "content": "11.3 x 15.9 cm. (4  7/16  x 6  1/4  in.)",
      "classified_as": [
        {
          "id": "http://vocab.getty.edu/aat/300266036",
          "type": "Type",
          "_label": "Dimension Statement"
        },
        {
          "id": "http://vocab.getty.edu/aat/300418049",
          "type": "Type",
          "_label": "Brief Text"
        }
      ]
    },
    {
      "id": "http://lod.example.org/museum/LinguisticObject/194",
      "type": "LinguisticObject",
      "content": "Anonymous Gift, 1977",
      "classified_as": [
        {
          "id": "http://vocab.getty.edu/aat/300026687",
          "type": "Type",
          "_label": "Credit Statement"
        },
        {
          "id": "http://vocab.getty.edu/aat/300418049",
          "type": "Type",
          "_label": "Brief Text"
        }
      ]
    },
    {
      "id": "http://lod.example.org/museum/LinguisticObject/195",
      "type": "LinguisticObject",
      "classified_as": [
        {
          "id": "http://vocab.getty.edu/aat/300080091",
          "type": "Type",
          "_label": "Description"
        },
        {
          "id": "http://vocab.getty.edu/aat/300418049",
          "type": "Type",
          "_label": "Brief Text"
        }
      ]
    }
  ],
  "representation": [
    {
      "type": "VisualItem",
      "classified_as": [
        {
          "id": "http://vocab.getty.edu/aat/300215302",
          "type": "Type",
          "_label": "Digital Image"
        }
      ]
    }
  ]
}